MANIFEST.in
README.rst
setup.py
tomaty/__init__.py
tomaty/__main__.py
tomaty/tomaty.py
tomaty/tomatyTimer.py
tomaty/tomaty_button.py
tomaty/tomaty_label.py
tomaty/tomaty_notebook.py
tomaty.egg-info/PKG-INFO
tomaty.egg-info/SOURCES.txt
tomaty.egg-info/dependency_links.txt
tomaty.egg-info/entry_points.txt
tomaty.egg-info/requires.txt
tomaty.egg-info/top_level.txt
tomaty/lib/__init__.py
tomaty/lib/serialization/__init__.py
tomaty/lib/serialization/tomaty_serialization.py
tomaty/lib/utilities/__init__.py
tomaty/lib/utilities/date_utilities.py
tomaty/resources/audio/alarm-original.wav
tomaty/resources/audio/alarm.wav
tomaty/resources/audio/copyright.txt