Metadata-Version: 1.0
Name: tomaty
Version: 1.0.3
Summary: tomaty is a pomodoro program featuring a GUI and tracking system
Home-page: https://github.com/ejmg/tomaty
Author: elias julian marko garcia
Author-email: elias.jm.garcia@gmail.com
License: MIT
Platform: UNKNOWN
